hsdpy/__init__.py
hsdpy/_ctypes_bindings.py
hsdpy/libhsd.so
hsdpy-0.1.0.dist-info/licenses/LICENSE
hsdpy-0.1.0.dist-info/METADATA
hsdpy-0.1.0.dist-info/WHEEL
hsdpy-0.1.0.dist-info/top_level.txt
hsdpy-0.1.0.dist-info/RECORD
