Metadata-Version: 2.4
Name: hsdpy
Version: 0.1.0
Summary: Python bindings for the Hsdlib library
Author-email: Hassan Abedi <hassan.abedi.t+hsdlib@gmail.com>
License: MIT
Project-URL: Repository, https://github.com/habedi/hsdlib
Project-URL: Issues, https://github.com/habedi/hsdlib/issues
Keywords: python binding,simd,distance metrics,similarity measures
Classifier: Development Status :: 4 - Beta
Classifier: Intended Audience :: Developers
Classifier: License :: OSI Approved :: MIT License
Classifier: Programming Language :: Python :: 3
Classifier: Programming Language :: Python :: 3.10
Classifier: Programming Language :: Python :: 3.11
Classifier: Programming Language :: Python :: 3.12
Classifier: Programming Language :: Python :: 3.13
Requires-Python: >=3.10
License-File: LICENSE
Requires-Dist: numpy<3.0.0,>=2.0.0
Provides-Extra: dev
Requires-Dist: pre-commit<5.0.0,>=4.2.0; extra == "dev"
Requires-Dist: pytest<9.0.0,>=8.0.1; extra == "dev"
Requires-Dist: pytest-cov<7.0.0,>=6.0.0; extra == "dev"
Requires-Dist: pyright<2.0.0,>=1.1.391; extra == "dev"
Requires-Dist: ruff<1.0.0,>=0.9.3; extra == "dev"
Requires-Dist: scipy<2.0.0,>=1.15.2; extra == "dev"
Dynamic: license-file
